[
null,
{"id":1,"actions":[{"conditionParam1":63,"conditionParam2":0,"conditionType":6,"rating":5,"skillId":1},{"conditionParam1":0,"conditionParam2":0,"conditionType":0,"rating":3,"skillId":7}],"battlerHue":0,"battlerName":"Rogue","dropItems":[{"kind":1,"dataId":1,"denominator":3},{"kind":1,"dataId":5,"denominator":5},{"dataId":1,"denominator":1,"kind":0}],"exp":1000,"traits":[{"code":22,"dataId":0,"value":0.95},{"code":22,"dataId":1,"value":0.05},{"code":31,"dataId":1,"value":0}],"gold":0,"name":"下級盜賊","note":"","params":[200,0,30,50,20,20,30,20]},
{"id":2,"actions":[{"conditionParam1":63,"conditionParam2":0,"conditionType":6,"rating":5,"skillId":1}],"battlerHue":0,"battlerName":"Swordsman","dropItems":[{"kind":1,"dataId":1,"denominator":3},{"kind":1,"dataId":5,"denominator":5},{"dataId":1,"denominator":1,"kind":0}],"exp":2000,"traits":[{"code":22,"dataId":0,"value":0.95},{"code":22,"dataId":1,"value":0.05},{"code":31,"dataId":1,"value":0}],"gold":0,"name":"中級盜賊","note":"","params":[2000,0,25,40,20,20,30,20]},
{"id":3,"actions":[{"conditionParam1":63,"conditionParam2":0,"conditionType":6,"rating":5,"skillId":1},{"conditionParam1":0,"conditionParam2":0,"conditionType":0,"rating":3,"skillId":8}],"battlerHue":0,"battlerName":"Rogue_double","dropItems":[{"kind":1,"dataId":1,"denominator":2},{"kind":1,"dataId":5,"denominator":3},{"kind":1,"dataId":6,"denominator":5}],"exp":2000,"traits":[{"code":22,"dataId":0,"value":0.95},{"code":22,"dataId":1,"value":0.05},{"code":31,"dataId":1,"value":0}],"gold":0,"name":"下級盜賊們","note":"","params":[400,0,40,60,20,20,50,20]},
{"id":4,"actions":[{"conditionParam1":63,"conditionParam2":0,"conditionType":6,"rating":5,"skillId":1}],"battlerHue":0,"battlerName":"Actor1_7","dropItems":[{"kind":1,"dataId":1,"denominator":3},{"kind":1,"dataId":5,"denominator":5},{"dataId":1,"denominator":1,"kind":0}],"exp":5000,"traits":[{"code":22,"dataId":0,"value":0.95},{"code":22,"dataId":1,"value":0.05},{"code":31,"dataId":1,"value":0}],"gold":0,"name":"上級盜賊","note":"","params":[5000,0,60,50,20,20,30,20]}
]